data_objects/__init__.py
data_objects/agency.py
data_objects/base_object.py
data_objects/line.py
data_objects/route.py
data_objects/service.py
data_objects/shape.py
data_objects/stop.py
data_objects/stop_time.py
data_objects/trip.py
gtfs.py-0.1.dist-info/METADATA
gtfs.py-0.1.dist-info/RECORD
gtfs.py-0.1.dist-info/WHEEL
gtfs.py-0.1.dist-info/top_level.txt
gtfspy/__init__.py
gtfspy/transit_data_object.py
gtfspy/transit_data_utils.py
gtfspy/data_objects/__init__.py
gtfspy/data_objects/agency.py
gtfspy/data_objects/base_object.py
gtfspy/data_objects/fare_attribute.py
gtfspy/data_objects/fare_rule.py
gtfspy/data_objects/line.py
gtfspy/data_objects/route.py
gtfspy/data_objects/service.py
gtfspy/data_objects/shape.py
gtfspy/data_objects/stop.py
gtfspy/data_objects/stop_time.py
gtfspy/data_objects/translator.py
gtfspy/data_objects/trip.py
gtfspy/data_objects/unknown_file.py
gtfspy/utils/__init__.py
gtfspy/utils/lines_factory.py
gtfspy/utils/parsing.py
gtfspy/utils/time.py
gtfspy/utils/transit_data_utils.py
gtfspy/utils/validating.py
utils/__init__.py
utils/lines_factory.py
utils/parsing.py
utils/time.py
