Metadata-Version: 2.1
Name: gtfs.py
Version: 0.1
Summary: A simple python library for parsing, editing and writing GTFS files
Home-page: https://github.com/WYishai/gtfs.py
Author: Yishai Wiesner
Author-email: wyishai@gmail.com
License: UNKNOWN
Platform: UNKNOWN
Classifier: Development Status :: 4 - Beta
Classifier: Intended Audience :: Developers
Classifier: Intended Audience :: Information Technology
Classifier: Intended Audience :: Other Audience
Classifier: License :: OSI Approved :: Apache Software License
Classifier: Operating System :: OS Independent
Classifier: Programming Language :: Python :: 2.7
Classifier: Topic :: Scientific/Engineering :: GIS
Classifier: Topic :: Software Development :: Libraries :: Python Modules
Requires-Dist: sortedcontainers
